[{"player": "Artur Boruc", "minutes": 90, "goals": 0, "assists": 0, "shots": 0, "shots_on_target": 0, "shot_accuracy": 0, "xg": 0.0, "xg_per_90": 0.0, "xa": 0, "xa_per_90": 0.0, "goals_per_90": 0.0, "passes": 49, "passes_completed": 29, "pass_completion_pct": 59.2, "key_passes": 0, "progressive_passes": 42, "passes_into_final_third": 3, "crosses": 0, "through_balls": 0, "switches": 2, "dribbles": 0, "dribbles_completed": 0, "dribble_success_pct": 0, "carries": 12, "progressive_carries": 0, "duels": 0, "duels_won": 0, "duel_success_pct": 0, "tackles": 0, "tackles_won": 0, "tackle_success_pct": 0, "aerial_duels": 0, "aerial_duels_won": 0, "aerial_success_pct": 0, "pressures": 0, "interceptions": 0, "clearances": 1, "blocks": 0, "ball_recoveries": 7, "fouls_committed": 0, "fouls_won": 0, "dispossessed": 0, "miscontrols": 0, "dribbled_past": 0, "match_id": 3754058, "team": "AFC Bournemouth", "competition": "Premier League", "season": "2015/2016"}, {"player": "Artur Boruc", "minutes": 88, "goals": 0, "assists": 0, "shots": 0, "shots_on_target": 0, "shot_accuracy": 0, "xg": 0.0, "xg_per_90": 0.0, "xa": 0, "xa_per_90": 0.0, "goals_per_90": 0.0, "passes": 27, "passes_completed": 14, "pass_completion_pct": 51.9, "key_passes": 0, "progressive_passes": 24, "passes_into_final_third": 2, "crosses": 0, "through_balls": 0, "switches": 2, "dribbles": 1, "dribbles_completed": 1, "dribble_success_pct": 100.0, "carries": 14, "progressive_carries": 0, "duels": 0, "duels_won": 0, "duel_success_pct": 0, "tackles": 0, "tackles_won": 0, "tackle_success_pct": 0, "aerial_duels": 0, "aerial_duels_won": 0, "aerial_success_pct": 0, "pressures": 1, "interceptions": 0, "clearances": 0, "blocks": 0, "ball_recoveries": 4, "fouls_committed": 0, "fouls_won": 0, "dispossessed": 0, "miscontrols": 0, "dribbled_past": 0, "match_id": 3754037, "team": "AFC Bournemouth", "competition": "Premier League", "season": "2015/2016"}, {"player": "Artur Boruc", "minutes": 92, "goals": 0, "assists": 0, "shots": 0, "shots_on_target": 0, "shot_accuracy": 0, "xg": 0.0, "xg_per_90": 0.0, "xa": 0, "xa_per_90": 0.0, "goals_per_90": 0.0, "passes": 33, "passes_completed": 17, "pass_completion_pct": 51.5, "key_passes": 0, "progressive_passes": 29, "passes_into_final_third": 2, "crosses": 0, "through_balls": 0, "switches": 0, "dribbles": 0, "dribbles_completed": 0, "dribble_success_pct": 0, "carries": 10, "progressive_carries": 0, "duels": 0, "duels_won": 0, "duel_success_pct": 0, "tackles": 0, "tackles_won": 0, "tackle_success_pct": 0, "aerial_duels": 0, "aerial_duels_won": 0, "aerial_success_pct": 0, "pressures": 0, "interceptions": 0, "clearances": 0, "blocks": 0, "ball_recoveries": 2, "fouls_committed": 0, "fouls_won": 0, "dispossessed": 0, "miscontrols": 0, "dribbled_past": 0, "match_id": 3754043, "team": "AFC Bournemouth", "competition": "Premier League", "season": "2015/2016"}, {"player": "Artur Boruc", "minutes": 108, "goals": 0, "assists": 0, "shots": 0, "shots_on_target": 0, "shot_accuracy": 0, "xg": 0.0, "xg_per_90": 0.0, "xa": 0, "xa_per_90": 0.0, "goals_per_90": 0.0, "passes": 30, "passes_completed": 21, "pass_completion_pct": 70.0, "key_passes": 0, "progressive_passes": 28, "passes_into_final_third": 2, "crosses": 0, "through_balls": 0, "switches": 0, "dribbles": 0, "dribbles_completed": 0, "dribble_success_pct": 0, "carries": 15, "progressive_carries": 2, "duels": 0, "duels_won": 0, "duel_success_pct": 0, "tackles": 0, "tackles_won": 0, "tackle_success_pct": 0, "aerial_duels": 0, "aerial_duels_won": 0, "aerial_success_pct": 0, "pressures": 0, "interceptions": 0, "clearances": 0, "blocks": 0, "ball_recoveries": 8, "fouls_committed": 0, "fouls_won": 0, "dispossessed": 0, "miscontrols": 0, "dribbled_past": 0, "match_id": 3754339, "team": "AFC Bournemouth", "competition": "Premier League", "season": "2015/2016"}, {"player": "Artur Boruc", "minutes": 89, "goals": 0, "assists": 0, "shots": 0, "shots_on_target": 0, "shot_accuracy": 0, "xg": 0.0, "xg_per_90": 0.0, "xa": 0, "xa_per_90": 0.0, "goals_per_90": 0.0, "passes": 25, "passes_completed": 17, "pass_completion_pct": 68.0, "key_passes": 0, "progressive_passes": 22, "passes_into_final_third": 1, "crosses": 0, "through_balls": 0, "switches": 0, "dribbles": 0, "dribbles_completed": 0, "dribble_success_pct": 0, "carries": 9, "progressive_carries": 0, "duels": 0, "duels_won": 0, "duel_success_pct": 0, "tackles": 0, "tackles_won": 0, "tackle_success_pct": 0, "aerial_duels": 0, "aerial_duels_won": 0, "aerial_success_pct": 0, "pressures": 0, "interceptions": 0, "clearances": 0, "blocks": 0, "ball_recoveries": 8, "fouls_committed": 0, "fouls_won": 0, "dispossessed": 0, "miscontrols": 0, "dribbled_past": 0, "match_id": 3754278, "team": "AFC Bournemouth", "competition": "Premier League", "season": "2015/2016"}, {"player": "Artur Boruc", "minutes": 92, "goals": 0, "assists": 0, "shots": 0, "shots_on_target": 0, "shot_accuracy": 0, "xg": 0.0, "xg_per_90": 0.0, "xa": 0, "xa_per_90": 0.0, "goals_per_90": 0.0, "passes": 21, "passes_completed": 12, "pass_completion_pct": 57.1, "key_passes": 0, "progressive_passes": 19, "passes_into_final_third": 2, "crosses": 0, "through_balls": 0, "switches": 1, "dribbles": 0, "dribbles_completed": 0, "dribble_success_pct": 0, "carries": 8, "progressive_carries": 0, "duels": 0, "duels_won": 0, "duel_success_pct": 0, "tackles": 0, "tackles_won": 0, "tackle_success_pct": 0, "aerial_duels": 0, "aerial_duels_won": 0, "aerial_success_pct": 0, "pressures": 0, "interceptions": 0, "clearances": 0, "blocks": 0, "ball_recoveries": 4, "fouls_committed": 0, "fouls_won": 0, "dispossessed": 0, "miscontrols": 0, "dribbled_past": 0, "match_id": 3754023, "team": "AFC Bournemouth", "competition": "Premier League", "season": "2015/2016"}]