[{"player": "Nathan Ngoumou Minpole", "minutes": 14, "goals": 0, "assists": 0, "shots": 0, "shots_on_target": 0, "shot_accuracy": 0, "xg": 0.0, "xg_per_90": 0.0, "xa": 0, "xa_per_90": 0.0, "goals_per_90": 0.0, "passes": 1, "passes_completed": 1, "pass_completion_pct": 100.0, "key_passes": 0, "progressive_passes": 0, "passes_into_final_third": 0, "crosses": 0, "through_balls": 0, "switches": 0, "dribbles": 0, "dribbles_completed": 0, "dribble_success_pct": 0, "carries": 2, "progressive_carries": 0, "duels": 1, "duels_won": 0, "duel_success_pct": 0.0, "tackles": 0, "tackles_won": 0, "tackle_success_pct": 0, "aerial_duels": 1, "aerial_duels_won": 0, "aerial_success_pct": 0.0, "pressures": 7, "interceptions": 0, "clearances": 1, "blocks": 0, "ball_recoveries": 1, "fouls_committed": 0, "fouls_won": 1, "dispossessed": 0, "miscontrols": 1, "dribbled_past": 0, "match_id": 3895210, "team": "Borussia M\u00f6nchengladbach", "competition": "Bundesliga", "season": "2023/2024"}, {"player": "Nathan Ngoumou Minpole", "minutes": 66, "goals": 0, "assists": 0, "shots": 0, "shots_on_target": 0, "shot_accuracy": 0, "xg": 0.0, "xg_per_90": 0.0, "xa": 0, "xa_per_90": 0.0, "goals_per_90": 0.0, "passes": 26, "passes_completed": 21, "pass_completion_pct": 80.8, "key_passes": 2, "progressive_passes": 8, "passes_into_final_third": 13, "crosses": 1, "through_balls": 0, "switches": 0, "dribbles": 0, "dribbles_completed": 0, "dribble_success_pct": 0, "carries": 27, "progressive_carries": 6, "duels": 5, "duels_won": 2, "duel_success_pct": 40.0, "tackles": 3, "tackles_won": 2, "tackle_success_pct": 66.7, "aerial_duels": 2, "aerial_duels_won": 0, "aerial_success_pct": 0.0, "pressures": 24, "interceptions": 1, "clearances": 0, "blocks": 1, "ball_recoveries": 6, "fouls_committed": 1, "fouls_won": 1, "dispossessed": 3, "miscontrols": 1, "dribbled_past": 2, "match_id": 3895060, "team": "Borussia M\u00f6nchengladbach", "competition": "Bundesliga", "season": "2023/2024"}]