[{"player": "Hugo Miguel Pereira de Almeida", "minutes": 88, "goals": 0, "assists": 0, "shots": 3, "shots_on_target": 0, "shot_accuracy": 0.0, "xg": 0.12, "xg_per_90": 0.12, "xa": 0, "xa_per_90": 0.0, "goals_per_90": 0.0, "passes": 37, "passes_completed": 19, "pass_completion_pct": 51.4, "key_passes": 1, "progressive_passes": 16, "passes_into_final_third": 19, "crosses": 1, "through_balls": 0, "switches": 0, "dribbles": 0, "dribbles_completed": 0, "dribble_success_pct": 0, "carries": 14, "progressive_carries": 0, "duels": 9, "duels_won": 1, "duel_success_pct": 11.1, "tackles": 2, "tackles_won": 1, "tackle_success_pct": 50.0, "aerial_duels": 7, "aerial_duels_won": 0, "aerial_success_pct": 0.0, "pressures": 8, "interceptions": 0, "clearances": 2, "blocks": 0, "ball_recoveries": 1, "fouls_committed": 0, "fouls_won": 0, "dispossessed": 1, "miscontrols": 1, "dribbled_past": 0, "match_id": 3890427, "team": "Hannover 96", "competition": "Bundesliga", "season": "2015/2016"}]