[{"player": "Jordi Xumetra Feliu", "minutes": 74, "goals": 0, "assists": 0, "shots": 2, "shots_on_target": 1, "shot_accuracy": 50.0, "xg": 0.45, "xg_per_90": 0.55, "xa": 0, "xa_per_90": 0.0, "goals_per_90": 0.0, "passes": 25, "passes_completed": 14, "pass_completion_pct": 56.0, "key_passes": 0, "progressive_passes": 5, "passes_into_final_third": 7, "crosses": 3, "through_balls": 0, "switches": 0, "dribbles": 0, "dribbles_completed": 0, "dribble_success_pct": 0, "carries": 18, "progressive_carries": 1, "duels": 3, "duels_won": 0, "duel_success_pct": 0.0, "tackles": 1, "tackles_won": 0, "tackle_success_pct": 0.0, "aerial_duels": 2, "aerial_duels_won": 0, "aerial_success_pct": 0.0, "pressures": 15, "interceptions": 0, "clearances": 0, "blocks": 1, "ball_recoveries": 6, "fouls_committed": 0, "fouls_won": 0, "dispossessed": 1, "miscontrols": 2, "dribbled_past": 0, "match_id": 3825902, "team": "Levante UD", "competition": "La Liga", "season": "2015/2016"}, {"player": "Jordi Xumetra Feliu", "minutes": 8, "goals": 0, "assists": 0, "shots": 0, "shots_on_target": 0, "shot_accuracy": 0, "xg": 0.0, "xg_per_90": 0.0, "xa": 0, "xa_per_90": 0.0, "goals_per_90": 0.0, "passes": 5, "passes_completed": 4, "pass_completion_pct": 80.0, "key_passes": 0, "progressive_passes": 3, "passes_into_final_third": 3, "crosses": 0, "through_balls": 0, "switches": 0, "dribbles": 1, "dribbles_completed": 0, "dribble_success_pct": 0.0, "carries": 4, "progressive_carries": 0, "duels": 0, "duels_won": 0, "duel_success_pct": 0, "tackles": 0, "tackles_won": 0, "tackle_success_pct": 0, "aerial_duels": 0, "aerial_duels_won": 0, "aerial_success_pct": 0, "pressures": 2, "interceptions": 0, "clearances": 0, "blocks": 1, "ball_recoveries": 0, "fouls_committed": 0, "fouls_won": 0, "dispossessed": 1, "miscontrols": 0, "dribbled_past": 0, "match_id": 3825825, "team": "Levante UD", "competition": "La Liga", "season": "2015/2016"}]