[{"player": "David \u00c1ngel Abraham", "minutes": 85, "goals": 0, "assists": 0, "shots": 1, "shots_on_target": 1, "shot_accuracy": 100.0, "xg": 0.04, "xg_per_90": 0.04, "xa": 0, "xa_per_90": 0.0, "goals_per_90": 0.0, "passes": 31, "passes_completed": 17, "pass_completion_pct": 54.8, "key_passes": 0, "progressive_passes": 20, "passes_into_final_third": 5, "crosses": 0, "through_balls": 0, "switches": 4, "dribbles": 0, "dribbles_completed": 0, "dribble_success_pct": 0, "carries": 14, "progressive_carries": 1, "duels": 7, "duels_won": 2, "duel_success_pct": 28.6, "tackles": 3, "tackles_won": 2, "tackle_success_pct": 66.7, "aerial_duels": 4, "aerial_duels_won": 0, "aerial_success_pct": 0.0, "pressures": 12, "interceptions": 2, "clearances": 4, "blocks": 4, "ball_recoveries": 12, "fouls_committed": 2, "fouls_won": 1, "dispossessed": 0, "miscontrols": 0, "dribbled_past": 1, "match_id": 3890521, "team": "Eintracht Frankfurt", "competition": "Bundesliga", "season": "2015/2016"}, {"player": "David \u00c1ngel Abraham", "minutes": 90, "goals": 0, "assists": 0, "shots": 0, "shots_on_target": 0, "shot_accuracy": 0, "xg": 0.0, "xg_per_90": 0.0, "xa": 0, "xa_per_90": 0.0, "goals_per_90": 0.0, "passes": 28, "passes_completed": 21, "pass_completion_pct": 75.0, "key_passes": 0, "progressive_passes": 16, "passes_into_final_third": 4, "crosses": 0, "through_balls": 0, "switches": 0, "dribbles": 0, "dribbles_completed": 0, "dribble_success_pct": 0, "carries": 15, "progressive_carries": 0, "duels": 8, "duels_won": 1, "duel_success_pct": 12.5, "tackles": 4, "tackles_won": 1, "tackle_success_pct": 25.0, "aerial_duels": 4, "aerial_duels_won": 0, "aerial_success_pct": 0.0, "pressures": 14, "interceptions": 2, "clearances": 6, "blocks": 4, "ball_recoveries": 3, "fouls_committed": 3, "fouls_won": 1, "dispossessed": 0, "miscontrols": 0, "dribbled_past": 0, "match_id": 3890370, "team": "Eintracht Frankfurt", "competition": "Bundesliga", "season": "2015/2016"}]