[{"player": "Marcel Risse", "minutes": 90, "goals": 0, "assists": 0, "shots": 0, "shots_on_target": 0, "shot_accuracy": 0, "xg": 0.0, "xg_per_90": 0.0, "xa": 0, "xa_per_90": 0.0, "goals_per_90": 0.0, "passes": 58, "passes_completed": 39, "pass_completion_pct": 67.2, "key_passes": 3, "progressive_passes": 29, "passes_into_final_third": 29, "crosses": 6, "through_balls": 0, "switches": 6, "dribbles": 0, "dribbles_completed": 0, "dribble_success_pct": 0, "carries": 36, "progressive_carries": 5, "duels": 3, "duels_won": 1, "duel_success_pct": 33.3, "tackles": 1, "tackles_won": 1, "tackle_success_pct": 100.0, "aerial_duels": 2, "aerial_duels_won": 0, "aerial_success_pct": 0.0, "pressures": 11, "interceptions": 2, "clearances": 3, "blocks": 1, "ball_recoveries": 7, "fouls_committed": 2, "fouls_won": 0, "dispossessed": 2, "miscontrols": 1, "dribbled_past": 1, "match_id": 3890519, "team": "FC K\u00f6ln", "competition": "Bundesliga", "season": "2015/2016"}, {"player": "Marcel Risse", "minutes": 90, "goals": 0, "assists": 1, "shots": 1, "shots_on_target": 0, "shot_accuracy": 0.0, "xg": 0.06, "xg_per_90": 0.06, "xa": 0, "xa_per_90": 0.0, "goals_per_90": 0.0, "passes": 64, "passes_completed": 34, "pass_completion_pct": 53.1, "key_passes": 4, "progressive_passes": 37, "passes_into_final_third": 31, "crosses": 8, "through_balls": 0, "switches": 1, "dribbles": 0, "dribbles_completed": 0, "dribble_success_pct": 0, "carries": 37, "progressive_carries": 8, "duels": 4, "duels_won": 2, "duel_success_pct": 50.0, "tackles": 3, "tackles_won": 2, "tackle_success_pct": 66.7, "aerial_duels": 1, "aerial_duels_won": 0, "aerial_success_pct": 0.0, "pressures": 14, "interceptions": 6, "clearances": 1, "blocks": 3, "ball_recoveries": 5, "fouls_committed": 0, "fouls_won": 1, "dispossessed": 1, "miscontrols": 0, "dribbled_past": 1, "match_id": 3890359, "team": "FC K\u00f6ln", "competition": "Bundesliga", "season": "2015/2016"}]