[{"player": "Jonathan Viera Ramos", "minutes": 77, "goals": 0, "assists": 0, "shots": 3, "shots_on_target": 1, "shot_accuracy": 33.3, "xg": 0.46, "xg_per_90": 0.54, "xa": 0, "xa_per_90": 0.0, "goals_per_90": 0.0, "passes": 41, "passes_completed": 28, "pass_completion_pct": 68.3, "key_passes": 1, "progressive_passes": 11, "passes_into_final_third": 26, "crosses": 6, "through_balls": 1, "switches": 3, "dribbles": 3, "dribbles_completed": 1, "dribble_success_pct": 33.3, "carries": 43, "progressive_carries": 5, "duels": 4, "duels_won": 0, "duel_success_pct": 0.0, "tackles": 0, "tackles_won": 0, "tackle_success_pct": 0, "aerial_duels": 4, "aerial_duels_won": 0, "aerial_success_pct": 0.0, "pressures": 17, "interceptions": 1, "clearances": 0, "blocks": 3, "ball_recoveries": 3, "fouls_committed": 1, "fouls_won": 2, "dispossessed": 3, "miscontrols": 3, "dribbled_past": 0, "match_id": 3825895, "team": "Las Palmas", "competition": "La Liga", "season": "2015/2016"}, {"player": "Jonathan Viera Ramos", "minutes": 92, "goals": 0, "assists": 0, "shots": 0, "shots_on_target": 0, "shot_accuracy": 0, "xg": 0.0, "xg_per_90": 0.0, "xa": 0, "xa_per_90": 0.0, "goals_per_90": 0.0, "passes": 78, "passes_completed": 68, "pass_completion_pct": 87.2, "key_passes": 1, "progressive_passes": 21, "passes_into_final_third": 33, "crosses": 3, "through_balls": 1, "switches": 7, "dribbles": 3, "dribbles_completed": 2, "dribble_success_pct": 66.7, "carries": 59, "progressive_carries": 5, "duels": 3, "duels_won": 0, "duel_success_pct": 0.0, "tackles": 0, "tackles_won": 0, "tackle_success_pct": 0, "aerial_duels": 3, "aerial_duels_won": 0, "aerial_success_pct": 0.0, "pressures": 13, "interceptions": 1, "clearances": 2, "blocks": 1, "ball_recoveries": 3, "fouls_committed": 0, "fouls_won": 2, "dispossessed": 1, "miscontrols": 1, "dribbled_past": 0, "match_id": 3825883, "team": "Las Palmas", "competition": "La Liga", "season": "2015/2016"}, {"player": "Jonathan Viera Ramos", "minutes": 92, "goals": 1, "assists": 2, "shots": 2, "shots_on_target": 2, "shot_accuracy": 100.0, "xg": 0.17, "xg_per_90": 0.17, "xa": 0, "xa_per_90": 0.0, "goals_per_90": 0.98, "passes": 81, "passes_completed": 66, "pass_completion_pct": 81.5, "key_passes": 4, "progressive_passes": 14, "passes_into_final_third": 38, "crosses": 1, "through_balls": 0, "switches": 0, "dribbles": 3, "dribbles_completed": 2, "dribble_success_pct": 66.7, "carries": 68, "progressive_carries": 7, "duels": 1, "duels_won": 0, "duel_success_pct": 0.0, "tackles": 0, "tackles_won": 0, "tackle_success_pct": 0, "aerial_duels": 1, "aerial_duels_won": 0, "aerial_success_pct": 0.0, "pressures": 32, "interceptions": 2, "clearances": 0, "blocks": 1, "ball_recoveries": 4, "fouls_committed": 1, "fouls_won": 3, "dispossessed": 0, "miscontrols": 1, "dribbled_past": 3, "match_id": 3825871, "team": "Las Palmas", "competition": "La Liga", "season": "2015/2016"}, {"player": "Jonathan Viera Ramos", "minutes": 90, "goals": 0, "assists": 0, "shots": 3, "shots_on_target": 0, "shot_accuracy": 0.0, "xg": 0.15, "xg_per_90": 0.15, "xa": 0, "xa_per_90": 0.0, "goals_per_90": 0.0, "passes": 75, "passes_completed": 67, "pass_completion_pct": 89.3, "key_passes": 1, "progressive_passes": 22, "passes_into_final_third": 24, "crosses": 1, "through_balls": 0, "switches": 1, "dribbles": 1, "dribbles_completed": 1, "dribble_success_pct": 100.0, "carries": 67, "progressive_carries": 12, "duels": 3, "duels_won": 1, "duel_success_pct": 33.3, "tackles": 2, "tackles_won": 1, "tackle_success_pct": 50.0, "aerial_duels": 1, "aerial_duels_won": 0, "aerial_success_pct": 0.0, "pressures": 13, "interceptions": 1, "clearances": 1, "blocks": 3, "ball_recoveries": 4, "fouls_committed": 1, "fouls_won": 0, "dispossessed": 3, "miscontrols": 2, "dribbled_past": 2, "match_id": 3825863, "team": "Las Palmas", "competition": "La Liga", "season": "2015/2016"}]